mab2rec/__init__.py
mab2rec/_version.py
mab2rec/pipeline.py
mab2rec/rec.py
mab2rec/utils.py
mab2rec/visualization.py
mab2rec-1.3.1.dist-info/LICENSE
mab2rec-1.3.1.dist-info/METADATA
mab2rec-1.3.1.dist-info/WHEEL
mab2rec-1.3.1.dist-info/top_level.txt
mab2rec-1.3.1.dist-info/RECORD
