Metadata-Version: 2.1
Name: mab2rec
Version: 1.3.1
Summary: Mab2Rec: Multi-Armed Bandits Recommender
Home-page: 
Author: FMR LLC
Project-URL: Source, https://github.com/fidelity/mab2rec
Classifier: License :: OSI Approved :: Apache Software License
Classifier: Programming Language :: Python :: 3.8
Classifier: Operating System :: OS Independent
Requires-Python: >=3.8
License-File: LICENSE
Requires-Dist: numpy >=1.20.2
Requires-Dist: pandas >=1.1.0
Requires-Dist: scikit-learn >=0.24.0
Requires-Dist: scipy
Requires-Dist: matplotlib
Requires-Dist: seaborn >=0.1.0
Requires-Dist: mabwiser >=2.7.4
Requires-Dist: jurity >=1.3.2
